aiokinesis/__init__.py
aiokinesis/consumer.py
aiokinesis/message_accumulator.py
aiokinesis/producer.py
aiokinesis/utils.py
aiokinesis-0.0.4.dist-info/METADATA
aiokinesis-0.0.4.dist-info/RECORD
aiokinesis-0.0.4.dist-info/WHEEL
aiokinesis-0.0.4.dist-info/top_level.txt
