Metadata-Version: 2.1
Name: aiokinesis
Version: 0.0.4
Summary: Asyncio kinesis client
Home-page: UNKNOWN
Author: Nik Liolios
Author-email: nik@asktetra.com
License: UNKNOWN
Platform: UNKNOWN
Classifier: License :: OSI Approved :: MIT License
Classifier: Intended Audience :: Developers
Classifier: Programming Language :: Python :: 3
Classifier: Programming Language :: Python :: 3.3
Classifier: Programming Language :: Python :: 3.4
Classifier: Programming Language :: Python :: 3.5
Classifier: Programming Language :: Python :: 3.6
Classifier: Operating System :: OS Independent
Classifier: Topic :: System :: Networking
Classifier: Topic :: System :: Distributed Computing
Classifier: Framework :: AsyncIO
Classifier: Development Status :: 4 - Beta
Requires-Dist: boto3 (==1.7.29)
